<keymap version="1" name="VSCode (Migrated)" parent="VSCode OSX">
  <action id="$Cut">
    <keyboard-shortcut first-keystroke="meta x" />
    <keyboard-shortcut first-keystroke="ctrl w" />
  </action>
  <action id="$Paste">
    <keyboard-shortcut first-keystroke="meta v" />
    <keyboard-shortcut first-keystroke="ctrl y" />
  </action>
  <action id="$Redo">
    <keyboard-shortcut first-keystroke="shift meta z" />
    <keyboard-shortcut first-keystroke="ctrl x" second-keystroke="ctrl r" />
  </action>
  <action id="$Undo">
    <keyboard-shortcut first-keystroke="meta z" />
    <keyboard-shortcut first-keystroke="ctrl x" second-keystroke="ctrl u" />
  </action>
  <action id="ActivateProjectToolWindow">
    <keyboard-shortcut first-keystroke="ctrl o" />
  </action>
  <action id="ActivateTerminalToolWindow">
    <keyboard-shortcut first-keystroke="ctrl back_quote" />
    <keyboard-shortcut first-keystroke="ctrl semicolon" />
  </action>
  <action id="CommentByLineComment">
    <keyboard-shortcut first-keystroke="meta k" second-keystroke="meta c" />
    <keyboard-shortcut first-keystroke="meta k" second-keystroke="meta u" />
    <keyboard-shortcut first-keystroke="meta slash" />
    <keyboard-shortcut first-keystroke="ctrl slash" />
  </action>
  <action id="Editor Redo">
    <keyboard-shortcut first-keystroke="ctrl x" second-keystroke="ctrl r" />
  </action>
  <action id="EditorBackSpace">
    <keyboard-shortcut first-keystroke="back_space" />
    <keyboard-shortcut first-keystroke="shift back_space" />
    <keyboard-shortcut first-keystroke="ctrl h" />
  </action>
  <action id="EditorCloneCaretAbove">
    <keyboard-shortcut first-keystroke="shift ctrl up" />
  </action>
  <action id="EditorCloneCaretBelow">
    <keyboard-shortcut first-keystroke="shift ctrl down" />
  </action>
  <action id="EditorCutLineEnd">
    <keyboard-shortcut first-keystroke="ctrl k" />
  </action>
  <action id="EditorDelete">
    <keyboard-shortcut first-keystroke="back_space" />
    <keyboard-shortcut first-keystroke="ctrl d" />
  </action>
  <action id="EditorDeleteLine" />
  <action id="EditorDeleteToLineEnd">
    <keyboard-shortcut first-keystroke="meta delete" />
  </action>
  <action id="EditorDuplicate">
    <keyboard-shortcut first-keystroke="meta d" />
  </action>
  <action id="EditorIndentLineOrSelection">
    <keyboard-shortcut first-keystroke="meta close_bracket" />
    <keyboard-shortcut first-keystroke="ctrl close_bracket" />
  </action>
  <action id="EditorJoinLines" />
  <action id="EditorLineEnd">
    <keyboard-shortcut first-keystroke="meta right" />
    <keyboard-shortcut first-keystroke="ctrl e" />
  </action>
  <action id="EditorLineStart">
    <keyboard-shortcut first-keystroke="meta left" />
    <keyboard-shortcut first-keystroke="ctrl a" />
  </action>
  <action id="EditorMatchBrace" />
  <action id="EditorSplitLine">
    <keyboard-shortcut first-keystroke="ctrl j" />
  </action>
  <action id="EditorToggleStickySelection">
    <keyboard-shortcut first-keystroke="ctrl u" />
  </action>
  <action id="EditorUnindentSelection">
    <keyboard-shortcut first-keystroke="meta open_bracket" />
    <keyboard-shortcut first-keystroke="shift tab" />
    <keyboard-shortcut first-keystroke="ctrl open_bracket" />
  </action>
  <action id="GotoLine">
    <keyboard-shortcut first-keystroke="ctrl g" />
    <keyboard-shortcut first-keystroke="shift meta g" />
  </action>
  <action id="GotoUrlAction" />
  <action id="MaximizeToolWindow" />
  <action id="MethodDown" />
  <action id="MethodUp" />
  <action id="MoveTabRight" />
  <action id="NextSplitter">
    <keyboard-shortcut first-keystroke="ctrl quote" />
  </action>
  <action id="NextTab">
    <keyboard-shortcut first-keystroke="ctrl tab" />
  </action>
  <action id="PrevSplitter">
    <keyboard-shortcut first-keystroke="ctrl meta quote" />
  </action>
  <action id="PreviousTab" />
  <action id="ReopenClosedTab">
    <keyboard-shortcut first-keystroke="shift meta w" />
  </action>
  <action id="Replace">
    <keyboard-shortcut first-keystroke="meta alt f" />
    <keyboard-shortcut first-keystroke="ctrl r" />
  </action>
  <action id="Rider.Plugins.FSharp.SendToFsi" />
  <action id="RiderTypeHierarchy.BaseOnThisType" />
  <action id="SelectAllOccurrences">
    <keyboard-shortcut first-keystroke="shift meta l" />
  </action>
  <action id="SplitHorizontally">
    <keyboard-shortcut first-keystroke="shift meta back_slash" />
  </action>
  <action id="Switcher">
    <keyboard-shortcut first-keystroke="shift ctrl tab" />
  </action>
  <action id="ToggleDistractionFreeMode">
    <keyboard-shortcut first-keystroke="meta z" second-keystroke="meta z" />
  </action>
  <action id="TypeHierarchy" />
  <action id="TypeHierarchyBase.BaseOnThisType" />
  <action id="UsageGrouping.DirectoryStructure" />
  <action id="com.jetbrains.rider.interactive.csi.SendToCSharpInteractive" />
</keymap>